dnevnik/Authenticator.py
dnevnik/Client.py
dnevnik/DnevnikClient.py
dnevnik/FileAuthenticator.py
dnevnik/IncorrectLoginPassword.py
dnevnik/PlayWrightAuthenticator.py
dnevnik/PredefinedAuthenticator.py
dnevnik/TOTPRequested.py
dnevnik/Utils.py
dnevnik/__init__.py
dnevnik_mos_ru_api-1.2.9.dist-info/METADATA
dnevnik_mos_ru_api-1.2.9.dist-info/WHEEL
dnevnik_mos_ru_api-1.2.9.dist-info/top_level.txt
dnevnik_mos_ru_api-1.2.9.dist-info/RECORD
