Metadata-Version: 2.1
Name: dnevnik-mos-ru-api
Version: 1.2.9
Summary: API for dnevnik.mos.ru
Author: RedGuy
License: MIT
Requires-Dist: playwright ==1.41.2
Requires-Dist: aiohttp ==3.9.3
Requires-Dist: mintotp ==0.3.0
Requires-Dist: pytz ==2024.1
